cpytest/__init__.py
cpytest/__main__.py
cpytest/codegen.py
cpytest/config.py
cpytest/cpyffi.py
cpytest/logger.py
cpytest/parse.py
cpytest/path_util.py
cpytest/preproc.py
cpytest/type.py
cpytest-0.1.2.dist-info/LICENSE
cpytest-0.1.2.dist-info/METADATA
cpytest-0.1.2.dist-info/WHEEL
cpytest-0.1.2.dist-info/entry_points.txt
cpytest-0.1.2.dist-info/RECORD
