Metadata-Version: 2.1
Name: cpytest
Version: 0.1.2
Summary: Test C Code using Python/pytest
Home-page: https://gitlab.com/janoskut/cpytest/-/tree/main
License: MIT
Author: Janos Kutscherauer
Author-email: janoskut@gmail.com
Requires-Python: >=3.9,<4.0
Classifier: License :: OSI Approved :: MIT License
Classifier: Programming Language :: Python :: 3
Classifier: Programming Language :: Python :: 3.9
Classifier: Programming Language :: Python :: 3.10
Classifier: Programming Language :: Python :: 3.11
Classifier: Programming Language :: Python :: 3.12
Requires-Dist: black (==23.11.0)
Requires-Dist: cffi (==1.16.0)
Requires-Dist: colorlog
Requires-Dist: pycparserext (==2021.1)
Requires-Dist: pyyaml (>=6.0,<7.0)
Requires-Dist: regex (==2023.10.3)
Requires-Dist: termcolor (>=2.4.0,<3.0.0)
Project-URL: Documentation, https://gitlab.com/janoskut/cpytest/-/blob/main/README.md
